gprint/__init__.py
gprint/gprint.py
gprint/test_gprint.py
gprint-0.0.9.dist-info/LICENSE
gprint-0.0.9.dist-info/METADATA
gprint-0.0.9.dist-info/WHEEL
gprint-0.0.9.dist-info/top_level.txt
gprint-0.0.9.dist-info/RECORD
