Metadata-Version: 2.1
Name: gprint
Version: 0.0.9
Summary: A fast way to print in color.
Home-page: https://github.com/guillerpsanchez/gprint
Author: Guillermo Peñarando Sánchez
Author-email: guillermo@guillerpsanchez.dev
License: MIT
Classifier: License :: OSI Approved :: MIT License
Classifier: Programming Language :: Python :: 3.11
Classifier: Programming Language :: Python :: 3.10
Classifier: Programming Language :: Python :: 3.9
Classifier: Programming Language :: Python :: 3.8
Classifier: Programming Language :: Python :: 3.7
Classifier: Programming Language :: Python :: 3.6
Classifier: Programming Language :: Python :: 3.5
Requires-Python: >=3.5
License-File: LICENSE
